{"inkVersion":19,"root":[["^Morning!","\n","ev","str","^Can't believe you remember my mornings when there's not even sunrises in hell.","/str","/ev",{"*":"0.c-0","flg":20},{"c-0":["^ ",{"->":"MorningsOnEarth"},"\n",{"->":"0.g-0"},{"#f":5}],"g-0":["done",{"#f":5}]}],"done",{"MorningsOnEarth":[["^it seems pretty important to you.","\n","ev","str","^Why do you say that?","/str","/ev",{"*":".^.c-0","flg":20},{"c-0":["^ ",{"->":"WhySayThat"},"\n",{"#f":5}]}],{"#f":1}],"WhySayThat":[["^Well you text me about it every 23 or so hours.","\n","^Texting the same thing that much, it must be pretty important.","\n","ev","str","^Am I texting you too much…","/str","/ev",{"*":".^.c-0","flg":20},{"c-0":["^ ",{"->":"TextingTooMuch"},"\n",{"#f":5}]}],{"#f":1}],"TextingTooMuch":[["^Are your thumbs hurting???","\n","ev","str","^No?","/str","/ev",{"*":".^.c-0","flg":20},{"c-0":["^ ",{"->":"ThumbsHurtNo"},"\n",{"#f":5}]}],{"#f":1}],"ThumbsHurtNo":[["^Then don’t overthink it. I like you, it’s fine.","\n","ev","str","^You like me?","/str","/ev",{"*":".^.c-0","flg":20},{"c-0":["^ ",{"->":"LikeMe"},"\n",{"#f":5}]}],{"#f":1}],"LikeMe":["^Don't overthink it.","\n","done",{"#f":1}],"#f":1}],"listDefs":{}}