{"inkVersion":19,"root":[[["^Hey I was thinking","\n",["^What kind of gifts do you like?","\n",["ev",{"^->":"0.g-0.g-1.2.$r1"},{"temp=":"$r"},"str",{"->":".^.s"},[{"#n":"$r1"}],"/str","/ev",{"*":".^.^.c-0","flg":18},{"s":["^woah! you don't need to do anything like that",{"->":"$r","var":true},null]}],{"c-0":["ev",{"^->":"0.g-0.g-1.c-0.$r2"},"/ev",{"temp=":"$r"},{"->":".^.^.2.s"},[{"#n":"$r2"}],"\n",{"->":"0.g-2"},{"#f":5}],"#f":5,"#n":"g-1"}],{"#f":5,"#n":"g-0"}],{"g-2":["^I'd like to","\n",["^besides, you don't need to feel weird about it","\n",["^it's common practice towards the end of a contract","\n",["ev",{"^->":"0.g-2.g-3.g-4.2.$r1"},{"temp=":"$r"},"str",{"->":".^.s"},[{"#n":"$r1"}],"/str","/ev",{"*":".^.^.c-1","flg":18},{"s":["^so your like paying me for my services?",{"->":"$r","var":true},null]}],{"c-1":["ev",{"^->":"0.g-2.g-3.g-4.c-1.$r2"},"/ev",{"temp=":"$r"},{"->":".^.^.2.s"},[{"#n":"$r2"}],"\n",{"->":"0.g-5"},{"#f":5}],"#f":5,"#n":"g-4"}],{"#f":5,"#n":"g-3"}],{"#f":5}],"g-5":["^...","\n",["^NO!","\n",["^i was just thinking about trying something nice!","\n",["ev",{"^->":"0.g-5.g-6.g-7.2.$r1"},{"temp=":"$r"},"str",{"->":".^.s"},[{"#n":"$r1"}],"/str","/ev",{"*":".^.^.c-2","flg":18},{"s":["^its okay, I'm only joking",{"->":"$r","var":true},null]}],{"c-2":["ev",{"^->":"0.g-5.g-6.g-7.c-2.$r2"},"/ev",{"temp=":"$r"},{"->":".^.^.2.s"},[{"#n":"$r2"}],"\n",{"->":"0.g-8"},{"#f":5}],"#f":5,"#n":"g-7"}],{"#f":5,"#n":"g-6"}],{"#f":5}],"g-8":["^And after I was trying to reward you","\n",["^...","\n",["^maybe you're more keen to punishment instead.","\n",["ev",{"^->":"0.g-8.g-9.g-10.2.$r1"},{"temp=":"$r"},"str",{"->":".^.s"},[{"#n":"$r1"}],"/str","/ev",{"*":".^.^.c-3","flg":18},{"s":["^You're always looking for an excuse to punish more",{"->":"$r","var":true},null]}],{"c-3":["ev",{"^->":"0.g-8.g-9.g-10.c-3.$r2"},"/ev",{"temp=":"$r"},{"->":".^.^.2.s"},[{"#n":"$r2"}],"\n",{"->":"0.g-11"},{"#f":5}],"#f":5,"#n":"g-10"}],{"#f":5,"#n":"g-9"}],{"#f":5}],"g-11":["^maybe you should stop enjoying it so much.","\n",["ev",{"^->":"0.g-11.2.$r1"},{"temp=":"$r"},"str",{"->":".^.s"},[{"#n":"$r1"}],"/str","/ev",{"*":".^.^.c-4","flg":18},{"s":["^that's not true",{"->":"$r","var":true},null]}],{"c-4":["ev",{"^->":"0.g-11.c-4.$r2"},"/ev",{"temp=":"$r"},{"->":".^.^.2.s"},[{"#n":"$r2"}],"\n",{"->":"0.g-12"},{"#f":5}],"#f":5}],"g-12":["^We're linked- whenever you feel pleasureee...","\n",["ev",{"^->":"0.g-12.2.$r1"},{"temp=":"$r"},"str",{"->":".^.s"},[{"#n":"$r1"}],"/str","/ev",{"*":".^.^.c-5","flg":18},{"s":["^okokok",{"->":"$r","var":true},null]}],{"c-5":["ev",{"^->":"0.g-12.c-5.$r2"},"/ev",{"temp=":"$r"},{"->":".^.^.2.s"},[{"#n":"$r2"}],"\n",{"->":"0.g-13"},{"#f":5}],"#f":5}],"g-13":["^hm I think I know what I can do.","\n",["ev",{"^->":"0.g-13.2.$r1"},{"temp=":"$r"},"str",{"->":".^.s"},[{"#n":"$r1"}],"/str","/ev",{"*":".^.^.c-6","flg":18},{"s":["^Anything but a gif",{"->":"$r","var":true},null]}],{"c-6":["ev",{"^->":"0.g-13.c-6.$r2"},"/ev",{"temp=":"$r"},{"->":".^.^.2.s"},[{"#n":"$r2"}],"\n",{"->":"0.g-14"},{"#f":5}],"#f":5}],"g-14":["^it's better","\n",["^put your phone on your thigh","\n",["^and don't pick up...","\n",["^did you like that?","\n",["ev",{"^->":"0.g-14.g-15.g-16.g-17.2.$r1"},{"temp=":"$r"},"str",{"->":".^.s"},[{"#n":"$r1"}],"/str","/ev",{"*":".^.^.c-7","flg":18},{"s":["^i wish i could feel you more",{"->":"$r","var":true},null]}],{"c-7":["ev",{"^->":"0.g-14.g-15.g-16.g-17.c-7.$r2"},"/ev",{"temp=":"$r"},{"->":".^.^.2.s"},[{"#n":"$r2"}],"\n",{"->":"0.g-18"},{"#f":5}],"#f":5,"#n":"g-17"}],{"#f":5,"#n":"g-16"}],{"#f":5,"#n":"g-15"}],{"#f":5}],"g-18":["^Well I want you to reward you a little more.","\n",["^Can you hear my voice in your head?","\n",["ev",{"^->":"0.g-18.g-19.2.$r1"},{"temp=":"$r"},"str",{"->":".^.s"},[{"#n":"$r1"}],"/str","/ev",{"*":".^.^.c-8","flg":18},{"s":["^What do you mean?",{"->":"$r","var":true},null]}],{"c-8":["ev",{"^->":"0.g-18.g-19.c-8.$r2"},"/ev",{"temp=":"$r"},{"->":".^.^.2.s"},[{"#n":"$r2"}],"\n",{"->":"0.g-20"},{"#f":5}],"#f":5,"#n":"g-19"}],{"#f":5}],"g-20":["^read my messages in my voice","\n",["^it'll make our link stronger.","\n",["^good bird","\n",["^Are you ready to follow my instructions?","\n",["ev",{"^->":"0.g-20.g-21.g-22.g-23.2.$r1"},{"temp=":"$r"},"str",{"->":".^.s"},[{"#n":"$r1"}],"/str","/ev",{"*":".^.^.c-9","flg":18},{"s":["^i'm nervous",{"->":"$r","var":true},null]}],{"c-9":["ev",{"^->":"0.g-20.g-21.g-22.g-23.c-9.$r2"},"/ev",{"temp=":"$r"},{"->":".^.^.2.s"},[{"#n":"$r2"}],"\n",{"->":"0.g-24"},{"#f":5}],"#f":5,"#n":"g-23"}],{"#f":5,"#n":"g-22"}],{"#f":5,"#n":"g-21"}],{"#f":5}],"g-24":["^It's okay, we'll only go as far as you want","\n",["ev",{"^->":"0.g-24.2.$r1"},{"temp=":"$r"},"str",{"->":".^.s"},[{"#n":"$r1"}],"/str","/ev",{"*":".^.^.c-10","flg":18},{"s":["^okay i'd like to play",{"->":"$r","var":true},null]}],{"c-10":["ev",{"^->":"0.g-24.c-10.$r2"},"/ev",{"temp=":"$r"},{"->":".^.^.2.s"},[{"#n":"$r2"}],"\n",{"->":"0.g-25"},{"#f":5}],"#f":5}],"g-25":["^Mm I was hoping my little bird would say that.","\n",["^Don't worry about texting back right now","\n",["^I want this to be a hands free experience","\n",["^Place me on some of your exposed skin if you can","\n",["^I want to feel you too","\n",["^ha remember I can feel anything you're doing","\n",["^I like it when you feel good","\n","done",["done",{"#f":5,"#n":"g-32"}],{"#f":5,"#n":"g-31"}],{"#f":5,"#n":"g-30"}],{"#f":5,"#n":"g-29"}],{"#f":5,"#n":"g-28"}],{"#f":5,"#n":"g-27"}],{"#f":5,"#n":"g-26"}],{"#f":5}]}],"done",{"#f":1}],"listDefs":{}}